gisweb_depag/__init__.py
gisweb_depag/config.py
gisweb_depag/depag.py
gisweb_depag/exceptions.py
gisweb_depag/schemas.py
gisweb_depag/templates/aggiornaDovuto.xml
gisweb_depag/templates/eliminaDovuto.xml
gisweb_depag/templates/generaAvviso.xml
gisweb_depag/templates/leggiDovuto.xml
gisweb_depag/templates/ricercaDovutiSoggetto.xml
gisweb_depag-0.1.3.dist-info/METADATA
gisweb_depag-0.1.3.dist-info/WHEEL
gisweb_depag-0.1.3.dist-info/RECORD
