Metadata-Version: 2.3
Name: gisweb-depag
Version: 0.1.3
Summary: Client SOAP per SIB.DEPAG
Author: Roberto Starnini
Author-email: roberto.starnini@gmail.com
Requires-Python: >3.9,<3.13
Classifier: Programming Language :: Python :: 3
Classifier: Programming Language :: Python :: 3.10
Classifier: Programming Language :: Python :: 3.11
Classifier: Programming Language :: Python :: 3.12
Requires-Dist: gisweb-pagopa-schema (>=0.1.1,<0.2.0)
Requires-Dist: httpx (>=0.28,<0.29)
Requires-Dist: jinja2 (>=3.1.2,<4.0.0)
Requires-Dist: pydantic[dotenv,email] (>=2.3.0,<3.0.0)
Requires-Dist: requests (>=2.31.0,<3.0.0)
Requires-Dist: zeep (>=4.2.1,<5.0.0)
